_atiiaftt.cp36-win_amd64.pyd
atiiaftt/__init__.py
atiiaftt/ft_interface.py
atiiaftt/samples/ftconvert.py
atiiaftt/test/__init__.py
atiiaftt/test/test_ft_iface.py
atiiaftt-0.1.1.dist-info/METADATA
atiiaftt-0.1.1.dist-info/RECORD
atiiaftt-0.1.1.dist-info/WHEEL
atiiaftt-0.1.1.dist-info/top_level.txt
