Metadata-Version: 2.1
Name: atiiaftt
Version: 0.1.1
Summary: CFFI wrap of ATI-IA force-torque sensor transform c library
Home-page: https://github.com/shayden--/atiiaftt
Author: Tyson Boer
Author-email: ty@unutilized.net
License: MIT
Download-URL: https://github.com/shayden--/atiiaftt/tarball/0.1.1
Keywords: ati,force,torque,sensor,instrumentation
Platform: UNKNOWN
Classifier: Intended Audience :: Manufacturing
Classifier: Intended Audience :: Science/Research
Classifier: License :: OSI Approved :: MIT License
Classifier: Operating System :: POSIX :: Linux
Classifier: Operating System :: Microsoft :: Windows
Classifier: Programming Language :: Python :: 2
Classifier: Programming Language :: Python :: 3
Classifier: Topic :: Scientific/Engineering
Requires-Dist: cffi (>=1.0.0)
